{
  "date": "2026.07.17",
  "weekday": "금",
  "juui": [
    {
      "name": "김금순",
      "vital": "-/측정안됨",
      "note": "머리감기를 어제 감으셨다며 거부하셨다가 다시 감으심. 워커를 이용해 걷는 것이 힘들다 하셔서 휠체어를 이용해 도움드림.",
      "tag": "거부"
    },
    {
      "name": "김민심",
      "vital": "-/측정안됨",
      "note": "어르신 대변 실수하셔서 직원 도움으로 물로 닦아드리고 기저귀 갈아드렸음.",
      "tag": "변실금"
    },
    {
      "name": "김종환",
      "vital": "-/측정안됨",
      "note": "어제보다는 배가 덜 아프다시고 대변도 정상변으로 보심. 식사는 잘하셨고 머리감기는 집에서 하고 오셨다며 거부하심. 노래봉사하는 아이를 흐뭇한 표정으로 보시고 호응도 잘해주심.",
      "tag": "거부"
    },
    {
      "name": "노남순",
      "vital": "-/측정안됨",
      "note": "⚠️ 오늘 요양·간호 기록 미입력(식사/화장실/특이사항 항목 공란). 프로그램 참여만 체크됨 — 확인 필요.",
      "tag": "기록미입력"
    },
    {
      "name": "박승유",
      "vital": "-/측정안됨",
      "note": "⚠️ 오늘 요양·간호 기록 미입력(식사/화장실/특이사항 항목 공란). 프로그램 참여만 체크됨 — 확인 필요.",
      "tag": "기록미입력"
    },
    {
      "name": "서계순",
      "vital": "-/측정안됨",
      "note": "⚠️ 오늘 요양·간호 기록 미입력(식사/화장실/특이사항 항목 공란). 프로그램 참여만 체크됨 — 확인 필요.",
      "tag": "기록미입력"
    },
    {
      "name": "송난식",
      "vital": "-/측정안됨",
      "note": "⚠️ 오늘 요양·간호 기록 미입력(식사/화장실/특이사항 항목 공란). 프로그램 참여만 체크됨 — 확인 필요.",
      "tag": "기록미입력"
    },
    {
      "name": "안재곤",
      "vital": "-/측정안됨",
      "note": "식사는 잘하셨지만 최근 식사 속도가 느려지는 경향이 있음. 개인위생 시간에 목욕도 잘하셨고 인지활동 시간에 발표도 잘하시는 모습을 보여주심. 안약을 계속 투약한 결과 점점 호전되는 모습을 보임. 안약을 넣어드리니 좋다고 하셨고 목욕 안내를 해드리니 하겠다고 말씀하셨음.",
      "tag": "안약"
    },
    {
      "name": "윤병대",
      "vital": "-/측정안됨",
      "note": "⚠️ 오늘 요양·간호 기록 미입력(식사/화장실/특이사항 항목 공란). 프로그램 참여만 체크됨 — 확인 필요.",
      "tag": "기록미입력"
    },
    {
      "name": "이남호",
      "vital": "-/측정안됨",
      "note": "직원의 도움을 거부하며 머리감기를 거부하셨음.",
      "tag": "거부"
    },
    {
      "name": "이복순",
      "vital": "-/측정안됨",
      "note": "⚠️ 오늘 요양·간호 기록 미입력(식사/화장실/특이사항 항목 공란). 프로그램 참여만 체크됨 — 확인 필요.",
      "tag": "기록미입력"
    },
    {
      "name": "이순봉",
      "vital": "-/측정안됨",
      "note": "눈자위가 벌겋게 되어있는 모습임. 눈에서 눈물이 난다고 하시고 자꾸 비비는 행동을 하심. 손의 위생상태가 그리 좋지 않아 비빌 때 자극이 되는 듯함, 되도록이면 자주 손을 씻을 수 있도록 권유함. 어제 양쪽 눈에 눈꼽이 끼여 있어서 오늘 눈 상태를 확인하니 심한 상태는 아니였고 눈 주위가 조금 빨간 상태여서 안약 넣어드렸음.",
      "tag": "안약"
    },
    {
      "name": "이원득",
      "vital": "-/측정안됨",
      "note": "오늘도 큰 거부감 없이 머리감기에 응해주셨고 평소와 달리 오전 오후 집에 가신다고는 하지 않으심.",
      "tag": "배회"
    },
    {
      "name": "이춘",
      "vital": "-/측정안됨",
      "note": "소변 및 대변 실수하셔서 기저귀를 착용하고 있으며 즉시 기저귀를 교체하고 피부상태를 관찰함.",
      "tag": "변실금"
    },
    {
      "name": "임명자",
      "vital": "-/측정안됨",
      "note": "⚠️ 오늘 요양·간호 기록 미입력(식사/화장실/특이사항 항목 공란). 프로그램 참여만 체크됨 — 확인 필요.",
      "tag": "기록미입력"
    },
    {
      "name": "정혜자",
      "vital": "-/측정안됨",
      "note": "⚠️ 오늘 요양·간호 기록 미입력(식사/화장실/특이사항 항목 공란). 프로그램 참여만 체크됨 — 확인 필요.",
      "tag": "기록미입력"
    },
    {
      "name": "조남석",
      "vital": "-/측정안됨",
      "note": "최근 규칙적으로 대변을 보지만 약간 설사를 하심. 배가 많이 아픈 것은 아니지만 약간 통증이 있다고 하심. 개인위생 시간에 목욕도 잘하셨고 인지활동 시간에 발표와 박수도 잘 치시면서 즐겁게 시간을 보내셨음. 오늘 에티켓에 대해서 배웠는데 어르신께 물어보니 기억을 하는 면을 보여주심. 남의 물건을 가져가면 안 된다고 다시 말씀드리니 웃으시면서 알겠다고 하심.",
      "tag": "설사,통증"
    },
    {
      "name": "최필하",
      "vital": "-/측정안됨",
      "note": "소변 실수를 하셔서 기저귀를 착용하고 있으며 기저귀를 교체하고 청결하게 피부상태를 확인하였음.",
      "tag": "변실금"
    },
    {
      "name": "홍기연",
      "vital": "-/측정안됨",
      "note": "어르신 뒷목이 불편하시다고 호소하셔서 파스 붙여드림. 머리감고 오셨다고 하시며 거부하심.",
      "tag": "거부"
    }
  ],
  "ilban": [
    {
      "name": "강유월",
      "vital": "-/측정안됨",
      "note": "아침 간식은 입맛이 없다시며 손도 대지 않으시길래 조금이라도 드셔야 약을 드실 수 있다고 말씀드리고 도움을 드리니 조금 드심. 눈이 자꾸 침침하다 하심. 눈물이 나거나 가렵거나 하진 않는다고 하심.",
      "tag": ""
    },
    {
      "name": "김명순",
      "vital": "-/측정안됨",
      "note": "머리도 잘 감으셨고 컨디션도 좋으신 듯 밝은 표정이심. 식사도 잘하심.",
      "tag": ""
    },
    {
      "name": "김정희",
      "vital": "-/측정안됨",
      "note": "오늘은 집에 가면 안 되냐는 질문은 하지 않으셨고 조용히 지내셨음. 점심 드시곤 야외에서 잠깐 계시다가 덥다며 금세 들어오셨음.",
      "tag": ""
    },
    {
      "name": "박일난",
      "vital": "-/측정안됨",
      "note": "머리감기는 잘하셨고 식사도 평상시처럼 드심. 노래봉사하는 아이 시간에도 참여하지 않으시고 자리에 누워 지내심.",
      "tag": ""
    },
    {
      "name": "유옥희",
      "vital": "-/측정안됨",
      "note": "청력과 시력이 저하되어 의사소통에 어려움이 있었으나 가까이에서 천천히 큰 목소리로 설명하며 반복해서 말씀드림.",
      "tag": ""
    },
    {
      "name": "유윤석",
      "vital": "-/측정안됨",
      "note": "최근 들어 화장실에서 대변을 많이 보는 경향이 있음. 어르신께도 물어보니 여전히 배 상태가 그렇게 좋지는 않다고 하심. 오전에 대변을 보시다가 바지에 묻어서 새 바지로 교체해드렸음. 개인위생 시간에 목욕도 잘하셨고 인지활동 시간에 발표도 잘하셨음. 바지에 대변이 묻었다고 말씀드리니 못 봤다고 하시면서 새로 옷을 가져다드리고 입던 옷은 새로 빨아드리겠다고 말씀드렸음. 어르신도 동의하셨음.",
      "tag": ""
    },
    {
      "name": "현순희",
      "vital": "-/측정안됨",
      "note": "어르신 기저귀에 잔변이 묻어나옴.",
      "tag": ""
    },
    {
      "name": "황운성",
      "vital": "-/측정안됨",
      "note": "오늘도 할당된 운동량을 완료했음. 식사는 잘하셨고 개인위생 시간에 목욕도 잘하셨고 인지활동 시간에 선생님의 도움을 받아 발표도 하고 즐거운 시간을 보내셨음. 운동을 하고자 하는 마음은 확실히 있지만 오늘은 쉬고 싶다는 의사를 표현하심. 그래도 운동을 한 후에 쉬도록 하는 것이 더 좋다고 말씀드리니 알았다고 하시면서 운동을 열심히 하셨음.",
      "tag": ""
    }
  ],
  "absent": [
    "김예금",
    "박영남",
    "양재표",
    "이정하"
  ]
}